odoo/addons/pos_payment_method_image/README.rst
odoo/addons/pos_payment_method_image/__init__.py
odoo/addons/pos_payment_method_image/__manifest__.py
odoo/addons/pos_payment_method_image/i18n/es.po
odoo/addons/pos_payment_method_image/i18n/fr.po
odoo/addons/pos_payment_method_image/i18n/it.po
odoo/addons/pos_payment_method_image/i18n/pos_payment_method_image.pot
odoo/addons/pos_payment_method_image/models/__init__.py
odoo/addons/pos_payment_method_image/models/pos_payment_method.py
odoo/addons/pos_payment_method_image/models/pos_session.py
odoo/addons/pos_payment_method_image/readme/CONFIGURE.rst
odoo/addons/pos_payment_method_image/readme/CONTRIBUTORS.rst
odoo/addons/pos_payment_method_image/readme/DESCRIPTION.rst
odoo/addons/pos_payment_method_image/readme/ROADMAP.rst
odoo/addons/pos_payment_method_image/static/description/icon.png
odoo/addons/pos_payment_method_image/static/description/index.html
odoo/addons/pos_payment_method_image/static/description/pos_payment.png
odoo/addons/pos_payment_method_image/static/description/pos_payment_method_form.png
odoo/addons/pos_payment_method_image/static/src/css/pos_payment_method_image.css
odoo/addons/pos_payment_method_image/static/src/img/card-bank.png
odoo/addons/pos_payment_method_image/static/src/img/money.png
odoo/addons/pos_payment_method_image/static/src/img/pay-later.png
odoo/addons/pos_payment_method_image/static/src/js/PaymentScreen.js
odoo/addons/pos_payment_method_image/static/src/xml/pos_payment_method_image.xml
odoo/addons/pos_payment_method_image/views/view_pos_payment_method.xml
odoo_addon_pos_payment_method_image-16.0.1.0.0.6.dist-info/METADATA
odoo_addon_pos_payment_method_image-16.0.1.0.0.6.dist-info/WHEEL
odoo_addon_pos_payment_method_image-16.0.1.0.0.6.dist-info/top_level.txt
odoo_addon_pos_payment_method_image-16.0.1.0.0.6.dist-info/RECORD
