Metadata-Version: 2.1
Name: odoo-addon-pos-payment-method-image
Version: 16.0.1.0.0.6
Summary: Add images on Payment Methods available in the PoS
Home-page: https://github.com/OCA/pos
Author: Odoo SA, GRAP, Odoo Community Association (OCA)
Author-email: support@odoo-community.org
License: LGPL-3
Platform: UNKNOWN
Classifier: Programming Language :: Python
Classifier: Framework :: Odoo
Classifier: Framework :: Odoo :: 16.0
Classifier: License :: OSI Approved :: GNU Lesser General Public License v3 (LGPLv3)
Requires-Python: >=3.10
Requires-Dist: odoo <16.1dev,>=16.0a
